pypak/__init__.py
pypak/anything.py
pypak-2.0.0.post1.dist-info/LICENSE
pypak-2.0.0.post1.dist-info/LICENSE.md
pypak-2.0.0.post1.dist-info/METADATA
pypak-2.0.0.post1.dist-info/WHEEL
pypak-2.0.0.post1.dist-info/top_level.txt
pypak-2.0.0.post1.dist-info/RECORD
