Metadata-Version: 2.1
Name: pypak
Version: 2.0.0.post1
Summary: python-repo template
Home-page: https://github.com/reactive-firewall/pypak
Download-URL: https://github.com/reactive-firewall/pypak.git
Author: reactive-firewall
Author-email: reactive-firewall@users.noreply.github.com
License: MIT License
Classifier: Development Status :: 4 - Beta
Classifier: Environment :: Console
Classifier: Intended Audience :: Developers
Classifier: Operating System :: MacOS :: MacOS X
Classifier: Operating System :: POSIX :: Linux
Classifier: License :: OSI Approved :: MIT License
Classifier: Programming Language :: Python :: 3
Classifier: Programming Language :: Python :: 3 :: Only
Classifier: Programming Language :: Python :: 3.12
Classifier: Programming Language :: Python :: 3.11
Classifier: Programming Language :: Python :: 3.10
Classifier: Topic :: Software Development :: Libraries :: Python Modules
Classifier: Topic :: System :: Networking
Obsoletes: S
Obsoletes: e
Obsoletes: e
License-File: LICENSE
License-File: LICENSE.md
Requires-Dist: setuptools>=45.0
Requires-Dist: virtualenv>=15.0.1
Requires-Dist: six>=1.0.0
Requires-Dist: tox>=3.0.0
Requires-Dist: pip>=21.0
